[
    {
        "title": "Remolques porta Grupo electrógenos y Compresores",
        "description": "Diseñado para satisfacer las demandas del sector agrícola.",
        "image": "/images/productos/electrogenos-y-compresores0.webp"
    },
    {
        "title": "Remolques porta Grupo electrógenos y Compresores",
        "description": "Diseñado para satisfacer las demandas del sector agrícola.",
        "image": "/images/productos/electrogenos-y-compresores1.webp"
    },
    {
        "title": "Remolques porta Grupo electrógenos y Compresores",
        "description": "Diseñado para satisfacer las demandas del sector agrícola.",
        "image": "/images/productos/electrogenos-y-compresores2.webp"
    },
    {
        "title": "Remolques porta Grupo electrógenos y Compresores",
        "description": "Diseñado para satisfacer las demandas del sector agrícola.",
        "image": "/images/productos/electrogenos-y-compresores3.webp"
    }
]